commands/__init__.py
commands/aws_commands.py
commands/config_commands.py
commands/github_commands.py
commands/google_commands.py
commands/jira_commands.py
commands/neo4j_commands.py
commands/notion_commands.py
commands/project_commands.py
commands/sheet_to_neo4j_commands.py
tests/__init__.py
tests/test_github_api.py
tests/test_tpm.py
trilogy_tpm-0.3.4.data/scripts/tpm
utils/__init__.py
utils/aws_utils.py
utils/config_utils.py
utils/github_utils.py
utils/google_utils.py
utils/jira_utils.py
utils/neo4j_utils.py
utils/notion_utils.py
utils/project_utils.py
trilogy_tpm-0.3.4.dist-info/METADATA
trilogy_tpm-0.3.4.dist-info/WHEEL
trilogy_tpm-0.3.4.dist-info/entry_points.txt
trilogy_tpm-0.3.4.dist-info/top_level.txt
trilogy_tpm-0.3.4.dist-info/RECORD
