Metadata-Version: 2.4
Name: trilogy-tpm
Version: 0.3.4
Summary: TPM CLI - Tools for Technical Project Managers
Home-page: https://github.com/trilogy-group/tpm-cli
Author: Technical Project Managers
Author-email: dschwartz@trilogy.com
Classifier: Programming Language :: Python :: 3
Classifier: License :: OSI Approved :: MIT License
Classifier: Operating System :: OS Independent
Requires-Python: >=3.6
Requires-Dist: requests>=2.25.0
Requires-Dist: tabulate>=0.8.7
Requires-Dist: google-api-python-client>=2.0.0
Requires-Dist: google-auth-httplib2>=0.1.0
Requires-Dist: google-auth-oauthlib>=0.4.2
Requires-Dist: markdown>=3.3.4
Requires-Dist: beautifulsoup4>=4.9.3
Requires-Dist: boto3>=1.18.0
Requires-Dist: click>=8.0.0
Requires-Dist: jira>=3.0.0
Requires-Dist: rich>=10.0.0
Requires-Dist: tqdm>=4.60.0
Requires-Dist: neo4j-graphrag>=0.5.0
Dynamic: author
Dynamic: author-email
Dynamic: classifier
Dynamic: description
Dynamic: description-content-type
Dynamic: home-page
Dynamic: requires-dist
Dynamic: requires-python
Dynamic: summary
